{
  "_class": "text",
  "attributedString": {
    "_class": "attributedString",
    "attributes": [
      {
        "_class": "stringAttribute",
        "attributes": {
          "MSAttributedStringColorAttribute": {
            "_class": "color",
            "alpha": 1,
            "blue": 0.6862745098039216,
            "green": 0.6745098039215687,
            "red": 0.6705882352941176
          },
          "MSAttributedStringFontAttribute": {
            "_class": "fontDescriptor",
            "attributes": {
              "name": "LucidaGrande",
              "size": 20
            }
          },
          "paragraphStyle": {
            "_class": "paragraphStyle"
          }
        },
        "length": 3,
        "location": 0
      }
    ],
    "string": "Sec"
  },
  "automaticallyDrawOnUnderlyingPath": false,
  "booleanOperation": -1,
  "do_objectID": "39456384-D5EE-4E61-98AC-835395928047",
  "dontSynchroniseWithSymbol": false,
  "exportOptions": {
    "_class": "exportOptions",
    "do_objectID": "7B0C398B-D83C-4A84-8156-68B725F6FEF3",
    "exportFormats": [
    ],
    "includedLayerIds": [
    ],
    "layerOptions": 0,
    "shouldTrim": false
  },
  "frame": {
    "_class": "rect",
    "constrainProportions": false,
    "do_objectID": "16000BAA-21F1-446A-AA4A-96CF0849E254",
    "height": 23,
    "width": 51,
    "x": 9,
    "y": 10
  },
  "glyphBounds": "{{0, 4}, {32, 16}}",
  "isFixedToViewport": false,
  "isFlippedHorizontal": false,
  "isFlippedVertical": false,
  "isLocked": false,
  "isVisible": true,
  "layerListExpandedType": 0,
  "lineSpacingBehaviour": 2,
  "name": "Sec",
  "nameIsFixed": false,
  "resizingConstraint": 47,
  "resizingType": 0,
  "rotation": 0,
  "shouldBreakMaskChain": false,
  "style": {
    "_class": "style",
    "do_objectID": "FF7F03EA-C8B1-499B-916A-C60B43882DB9",
    "endMarkerType": 0,
    "miterLimit": 10,
    "startMarkerType": 0,
    "textStyle": {
      "_class": "textStyle",
      "do_objectID": "FEF6E86E-A913-4E99-964F-B9F2B9B55DFE",
      "encodedAttributes": {
        "MSAttributedStringColorAttribute": {
          "_class": "color",
          "alpha": 1,
          "blue": 0.6862745098039216,
          "green": 0.6745098039215687,
          "red": 0.6705882352941176
        },
        "MSAttributedStringFontAttribute": {
          "_class": "fontDescriptor",
          "attributes": {
            "name": "LucidaGrande",
            "size": 20
          }
        },
        "paragraphStyle": {
          "_class": "paragraphStyle"
        }
      },
      "verticalAlignment": 0
    },
    "windingRule": 1
  },
  "textBehaviour": 1
}