{
  "_class": "group",
  "booleanOperation": -1,
  "clippingMaskMode": 0,
  "do_objectID": "0B3B23AF-CFE8-4C84-B56A-3CCE9A0EEF21",
  "exportOptions": {
    "_class": "exportOptions",
    "do_objectID": "81713193-E981-4728-B46D-0D3FB46C9CCF",
    "exportFormats": [
    ],
    "includedLayerIds": [
    ],
    "layerOptions": 0,
    "shouldTrim": false
  },
  "frame": {
    "_class": "rect",
    "constrainProportions": true,
    "do_objectID": "EFA605AC-7121-4A2E-AE92-68CAC8CFD131",
    "height": 21,
    "width": 21,
    "x": 5,
    "y": 5
  },
  "hasClickThrough": false,
  "hasClippingMask": false,
  "isFixedToViewport": false,
  "isFlippedHorizontal": false,
  "isFlippedVertical": false,
  "isLocked": false,
  "isVisible": true,
  "layerListExpandedType": 2,
  "layers": [
    {
      "class": "group",
      "id": "3E05CB78-65B6-4EF0-84BB-C58F5E6C8B6B"
    },
    {
      "class": "rectangle",
      "id": "FE44EC02-68C0-4965-B10C-0A4B246D5739"
    }
  ],
  "name": "ic-baseline-directions-bike",
  "nameIsFixed": false,
  "resizingConstraint": 63,
  "resizingType": 0,
  "rotation": 0,
  "shouldBreakMaskChain": false,
  "style": {
    "_class": "style",
    "do_objectID": "FDC4EFF5-2751-431B-8156-14B7659959FB",
    "endMarkerType": 0,
    "miterLimit": 10,
    "startMarkerType": 0,
    "windingRule": 1
  }
}