{
  "_class": "shapeGroup",
  "booleanOperation": -1,
  "clippingMaskMode": 0,
  "do_objectID": "7F53319C-3777-454F-88F9-5C692EC0B711",
  "exportOptions": {
    "_class": "exportOptions",
    "do_objectID": "BD4A0F8D-7B4E-48AA-B028-305B4A12A84C",
    "exportFormats": [
    ],
    "includedLayerIds": [
    ],
    "layerOptions": 0,
    "shouldTrim": false
  },
  "frame": {
    "_class": "rect",
    "constrainProportions": false,
    "do_objectID": "FB5245E7-5560-4DFE-AC63-465904B09409",
    "height": 21.5,
    "width": 16.1,
    "x": 0.8899999999998727,
    "y": 0.4800000000000182
  },
  "hasClickThrough": false,
  "hasClippingMask": false,
  "isFixedToViewport": false,
  "isFlippedHorizontal": false,
  "isFlippedVertical": false,
  "isLocked": false,
  "isVisible": true,
  "layerListExpandedType": 1,
  "layers": [
    {
      "class": "shapePath",
      "id": "D9AD679D-FEA0-4002-9DA6-26C8767111F7"
    },
    {
      "class": "shapePath",
      "id": "91EAA25E-FC68-4093-88B8-D2DFB4EA2006"
    }
  ],
  "name": "Icon Shape",
  "nameIsFixed": false,
  "resizingConstraint": 63,
  "resizingType": 0,
  "rotation": 0,
  "shouldBreakMaskChain": false,
  "style": {
    "_class": "style",
    "do_objectID": "B5DF2382-E466-4BFD-BF3E-268320C8F594",
    "endMarkerType": 0,
    "fills": [
      {
        "_class": "fill",
        "color": {
          "_class": "color",
          "alpha": 1,
          "blue": 1,
          "green": 1,
          "red": 1
        },
        "fillType": 0,
        "isEnabled": true,
        "noiseIndex": 0,
        "noiseIntensity": 0,
        "patternFillType": 1,
        "patternTileScale": 1
      }
    ],
    "miterLimit": 10,
    "startMarkerType": 0,
    "windingRule": 0
  },
  "windingRule": 0
}