{
  "_class": "group",
  "booleanOperation": -1,
  "clippingMaskMode": 0,
  "do_objectID": "F1B75DD7-E305-4F96-96EE-229ECF7DFF94",
  "exportOptions": {
    "_class": "exportOptions",
    "exportFormats": [
    ],
    "includedLayerIds": [
    ],
    "layerOptions": 0,
    "shouldTrim": false
  },
  "frame": {
    "_class": "rect",
    "constrainProportions": false,
    "height": 122,
    "width": 216,
    "x": 1182,
    "y": 167
  },
  "hasClickThrough": false,
  "hasClippingMask": false,
  "isFixedToViewport": false,
  "isFlippedHorizontal": false,
  "isFlippedVertical": false,
  "isLocked": false,
  "isVisible": true,
  "layerListExpandedType": 0,
  "layers": [
    {
      "class": "rectangle",
      "id": "247D6973-A544-439C-B60D-FBC1DC4D634E"
    },
    {
      "class": "text",
      "id": "8C4B69AB-C1A3-4D7F-AA9E-2F5435B0DD01"
    },
    {
      "class": "text",
      "id": "86A2CABE-1D72-46AF-9B06-391AB43650BC"
    },
    {
      "class": "text",
      "id": "90504B31-4AD9-495B-ABFC-572EAB21CCA1"
    },
    {
      "class": "oval",
      "id": "BF655BC7-E45A-46B6-B989-1B4580AE7504"
    },
    {
      "class": "group",
      "id": "D14DFE7E-A2EA-4E2F-B231-3840EE397DCD"
    }
  ],
  "name": "Group 5",
  "nameIsFixed": false,
  "resizingConstraint": 63,
  "resizingType": 0,
  "rotation": 0,
  "shouldBreakMaskChain": false,
  "style": {
    "_class": "style",
    "endMarkerType": 0,
    "miterLimit": 10,
    "startMarkerType": 0,
    "windingRule": 1
  }
}